MANIFEST.in
__about__.py
setup.cfg
setup.py
juicy_fruits/__init__.py
juicy_fruits/audio.py
juicy_fruits/elasticsearch_index.py
juicy_fruits/newrelic_apm.py
juicy_fruits/redis_collection.py
juicy_fruits/rollbar_logger.py
juicy_fruits/rq_worker.py
juicy_fruits/taskman.py
juicy_fruits.egg-info/PKG-INFO
juicy_fruits.egg-info/SOURCES.txt
juicy_fruits.egg-info/dependency_links.txt
juicy_fruits.egg-info/requires.txt
juicy_fruits.egg-info/top_level.txt