Metadata-Version: 1.1
Name: juicy-fruits
Version: 0.4.1
Summary: A collection librairies to work with Juice
Home-page: https://github.com/mardix/juicy-fruits
Author: Mardix
Author-email: mardix@pylot.io
License: MIT
Download-URL: http://github.com/mardix/juicy-fruits/tarball/master
Keywords: juice,rq,queue,redis
Platform: any
Classifier: Environment :: Web Environment
Classifier: Intended Audience :: Developers
Classifier: License :: OSI Approved :: BSD License
Classifier: Operating System :: OS Independent
Classifier: Programming Language :: Python
Classifier: Programming Language :: Python :: 2
Classifier: Programming Language :: Python :: 2.6
Classifier: Programming Language :: Python :: 2.7
Classifier: Programming Language :: Python :: 3
Classifier: Programming Language :: Python :: 3.3
Classifier: Programming Language :: Python :: 3.4
Classifier: Topic :: Internet :: WWW/HTTP :: Dynamic Content
Classifier: Topic :: Software Development :: Libraries :: Python Modules
